setup.py
pyfasm/__init__.py
pyfasm/constants.py
pyfasm.egg-info/PKG-INFO
pyfasm.egg-info/SOURCES.txt
pyfasm.egg-info/dependency_links.txt
pyfasm.egg-info/top_level.txt
pyfasm/ressources/__init__.py
pyfasm/ressources/fasm.dll