Metadata-Version: 1.1
Name: pyfasm
Version: 1.0.0
Summary: Wrapper around fasm
Home-page: https://github.com/srounet/pyfasm
Author: Fabien Reboia
Author-email: srounet@gmail.com
License: BSD
Platform: UNKNOWN
Classifier: Programming Language :: Python :: 3.4
Classifier: Programming Language :: Assembly
Classifier: Environment :: Win32 (MS Windows)
Classifier: Intended Audience :: Developers
Classifier: License :: OSI Approved :: BSD License
